wallet/__init__.py
wallet/api_client.py
wallet/configuration.py
wallet/exceptions.py
wallet/model_utils.py
wallet/rest.py
wallet/api/__init__.py
wallet/api/advertisement_credits_api.py
wallet/api/analytics_api.py
wallet/api/apple_wallet_subscribers_api.py
wallet/api/billing_api.py
wallet/api/club_members__points_api.py
wallet/api/configuration_api.py
wallet/api/countries_api.py
wallet/api/customer_api.py
wallet/api/dashboard_api.py
wallet/api/dynamic_vouchers_api.py
wallet/api/employee_access_api.py
wallet/api/employee_api_keys_api.py
wallet/api/employees_api.py
wallet/api/image_grid_api.py
wallet/api/industries_api.py
wallet/api/info_genesis_reports_api.py
wallet/api/integrated_terminals_api.py
wallet/api/interactions_api.py
wallet/api/link_book_api.py
wallet/api/link_book_section_api.py
wallet/api/login_and_logout_api.py
wallet/api/membership_tiers_api.py
wallet/api/merchant_api.py
wallet/api/merchant_credits_api.py
wallet/api/merchant_urls_api.py
wallet/api/mobile_terminal_api.py
wallet/api/news_api.py
wallet/api/payment_designs_api.py
wallet/api/performances_api.py
wallet/api/promo_codes_api.py
wallet/api/settings_api.py
wallet/api/shopify_terminal_api.py
wallet/api/sms_api.py
wallet/api/static_voucher_campaign_groups_api.py
wallet/api/static_voucher_campaigns_api.py
wallet/api/static_vouchers_api.py
wallet/api/system_api.py
wallet/api/transaction_ledger_api.py
wallet/api/utilities_api.py
wallet/api/web_terminal_api.py
wallet/api/wix_terminal_api.py
wallet/api/woo_commerce_terminal_api.py
wallet/apis/__init__.py
wallet/model/__init__.py
wallet/model/advertisement_credit.py
wallet/model/advertisement_credit_broadcast.py
wallet/model/advertisement_credit_scan.py
wallet/model/agreement.py
wallet/model/alert.py
wallet/model/announcement.py
wallet/model/applicable_terminals.py
wallet/model/applicable_terminals_any_of.py
wallet/model/applicable_terminals_any_of1.py
wallet/model/applicable_terminals_any_of2.py
wallet/model/applicable_terminals_any_of3.py
wallet-2.1.525.dist-info/LICENSE
wallet-2.1.525.dist-info/METADATA
wallet-2.1.525.dist-info/WHEEL
wallet-2.1.525.dist-info/top_level.txt
wallet-2.1.525.dist-info/RECORD
