Metadata-Version: 2.1
Name: wallet
Version: 2.1.525
Summary: OpenAPI compliant library to access resources on the Wallet Inc. Platform
Home-page: 
Author: Development Team
Author-email: Wallet SDK Development Team <sdk-python@wallet.inc>
License: https://wallet.law
Project-URL: Homepage, https://wallet.inc
Project-URL: Documentation, https://hub.wallet.dev
Project-URL: Changelog, https://hub.wallet.dev/changelog
Project-URL: Repository, https://github.com/WalletInc/sdk-python
Project-URL: Bug Tracker, https://github.com/WalletInc/sdk-python/issues
Project-URL: Blog, https://the.wallet.blog
Project-URL: Platform, https://wall.et/login
Project-URL: Sign Up, https://wall.et/MUo79TOZN4gJ
Keywords: digital wallet,mobile wallet,wallet as a service,customer relationship management,marketing platform,fintech,saas
Classifier: Programming Language :: Python :: 3
Classifier: License :: OSI Approved :: MIT License
Classifier: Operating System :: OS Independent
Requires-Python: >=3.6
License-File: LICENSE
Requires-Dist: urllib3 (>=1.25.3)
Requires-Dist: python-dateutil
